toolmaker/__init__.py
toolmaker/__main__.py
toolmaker/_i18n.py
toolmaker/_meta.py
toolmaker/cli.py
toolmaker/core.py
toolmaker-0.0.7.dist-info/LICENSE.txt
toolmaker-0.0.7.dist-info/METADATA
toolmaker-0.0.7.dist-info/WHEEL
toolmaker-0.0.7.dist-info/entry_points.txt
toolmaker-0.0.7.dist-info/top_level.txt
toolmaker-0.0.7.dist-info/RECORD
