Metadata-Version: 2.1
Name: toolmaker
Version: 0.0.7
Summary: Make single-file builds of Python tools using zapp, shiv, or pex
Home-page: https://pypi.org/project/toolmaker/
Author: sinoroc
Author-email: sinoroc.code+python@gmail.com
License: Apache-2.0
Project-URL: GitLab, https://gitlab.com/sinoroc/toolmaker
Project-URL: GitHub, https://github.com/sinoroc/toolmaker
Platform: UNKNOWN
Requires-Dist: importlib-metadata
Requires-Dist: pex
Requires-Dist: shiv
Requires-Dist: zapp (>=0.0.6)
Provides-Extra: package
Requires-Dist: twine ; extra == 'package'
Requires-Dist: wheel ; extra == 'package'
Requires-Dist: zapp ; extra == 'package'
Provides-Extra: test
Requires-Dist: pytest ; extra == 'test'
Requires-Dist: pytest-pycodestyle ; extra == 'test'
Requires-Dist: pytest-pylint ; extra == 'test'
